baseten/__init__.py
baseten/baseten_deployed_model.py
baseten/cli.py
baseten/client_commands/baseten_cli.py
baseten/client_commands/dataset_cli.py
baseten/client_commands/finetuning_cli.py
baseten/client_commands/models_cli.py
baseten/client_commands/pretrained_cli.py
baseten/common/__init__.py
baseten/common/api.py
baseten/common/core.py
baseten/common/error_handler.py
baseten/common/files.py
baseten/common/lib_support.py
baseten/common/model_deployer.py
baseten/common/settings.py
baseten/common/tar.py
baseten/common/types.py
baseten/common/util.py
baseten/models/__init__.py
baseten/models/flan_t5.py
baseten/models/foundational_model.py
baseten/models/llama.py
baseten/models/stable_diffusion.py
baseten/models/util.py
baseten/models/whisper.py
baseten/training/__init__.py
baseten/training/datasets.py
baseten/training/finetuning.py
baseten/training/logs.py
baseten/training/utils.py
baseten-0.8.2.dist-info/METADATA
baseten-0.8.2.dist-info/WHEEL
baseten-0.8.2.dist-info/entry_points.txt
baseten-0.8.2.dist-info/RECORD
